odoo/addons/stock_move_manage_priority/README.rst
odoo/addons/stock_move_manage_priority/__init__.py
odoo/addons/stock_move_manage_priority/__manifest__.py
odoo/addons/stock_move_manage_priority/i18n/es.po
odoo/addons/stock_move_manage_priority/i18n/fr.po
odoo/addons/stock_move_manage_priority/i18n/it.po
odoo/addons/stock_move_manage_priority/i18n/stock_move_manage_priority.pot
odoo/addons/stock_move_manage_priority/models/__init__.py
odoo/addons/stock_move_manage_priority/models/res_company.py
odoo/addons/stock_move_manage_priority/models/res_config_settings.py
odoo/addons/stock_move_manage_priority/models/stock_move.py
odoo/addons/stock_move_manage_priority/readme/CONTRIBUTORS.rst
odoo/addons/stock_move_manage_priority/readme/DESCRIPTION.rst
odoo/addons/stock_move_manage_priority/readme/USAGE.rst
odoo/addons/stock_move_manage_priority/security/groups.xml
odoo/addons/stock_move_manage_priority/static/description/icon.png
odoo/addons/stock_move_manage_priority/static/description/index.html
odoo/addons/stock_move_manage_priority/tests/__init__.py
odoo/addons/stock_move_manage_priority/tests/test_manage_move_priority.py
odoo/addons/stock_move_manage_priority/views/res_config_settings_views.xml
odoo/addons/stock_move_manage_priority/views/stock_move_views.xml
odoo/addons/stock_move_manage_priority/views/stock_picking_views.xml
odoo_addon_stock_move_manage_priority-16.0.1.0.1.dist-info/METADATA
odoo_addon_stock_move_manage_priority-16.0.1.0.1.dist-info/WHEEL
odoo_addon_stock_move_manage_priority-16.0.1.0.1.dist-info/top_level.txt
odoo_addon_stock_move_manage_priority-16.0.1.0.1.dist-info/RECORD
